{
	"info": {
		"_postman_id": "8463cdaf-7212-4d88-85bd-859520cc16fb",
		"name": "InAdvance",
		"schema": "https://schema.getpostman.com/json/collection/v2.1.0/collection.json",
		"_exporter_id": "6278580"
	},
	"item": [
		{
			"name": "CREATE",
			"request": {
				"auth": {
					"type": "bearer",
					"bearer": [
						{
							"key": "token",
							"value": "{{jwt_token}}",
							"type": "string"
						}
					]
				},
				"method": "POST",
				"header": [
					{
						"key": "",
						"value": "",
						"disabled": true
					}
				],
				"body": {
					"mode": "raw",
					"raw": "{\r\n    \"name\": \"Juan Rodriguez\",\r\n    \"email\": \"juan@rodriguez.cl\",\r\n    \"password\": \"hunter2\",\r\n    \"phones\": [\r\n        {\r\n            \"number\": \"1234567\",\r\n            \"citycode\": \"1\",\r\n            \"contrycode\": \"57\"\r\n        }\r\n    ]\r\n}",
					"options": {
						"raw": {
							"language": "json"
						}
					}
				},
				"url": {
					"raw": "localhost:8080/api/v1/user",
					"host": [
						"localhost"
					],
					"port": "8080",
					"path": [
						"api",
						"v1",
						"user"
					]
				}
			},
			"response": []
		},
		{
			"name": "READ",
			"request": {
				"auth": {
					"type": "bearer",
					"bearer": [
						{
							"key": "token",
							"value": "{{jwt_token}}",
							"type": "string"
						}
					]
				},
				"method": "GET",
				"header": [],
				"url": {
					"raw": "localhost:8080/api/v1/user/all",
					"host": [
						"localhost"
					],
					"port": "8080",
					"path": [
						"api",
						"v1",
						"user",
						"all"
					]
				}
			},
			"response": []
		},
		{
			"name": "UPDATE",
			"request": {
				"auth": {
					"type": "bearer",
					"bearer": [
						{
							"key": "token",
							"value": "{{jwt_token}}",
							"type": "string"
						}
					]
				},
				"method": "PUT",
				"header": [],
				"body": {
					"mode": "raw",
					"raw": "",
					"options": {
						"raw": {
							"language": "json"
						}
					}
				},
				"url": {
					"raw": "localhost:8080/api/v1/user",
					"host": [
						"localhost"
					],
					"port": "8080",
					"path": [
						"api",
						"v1",
						"user"
					]
				}
			},
			"response": []
		},
		{
			"name": "DELETE",
			"request": {
				"auth": {
					"type": "bearer",
					"bearer": [
						{
							"key": "token",
							"value": "{{jwt_token}}",
							"type": "string"
						}
					]
				},
				"method": "DELETE",
				"header": [],
				"url": {
					"raw": "localhost:8080/api/v1/user?email=juan@rodriguez.cl",
					"host": [
						"localhost"
					],
					"port": "8080",
					"path": [
						"api",
						"v1",
						"user"
					],
					"query": [
						{
							"key": "email",
							"value": "juan@rodriguez.cl"
						}
					]
				}
			},
			"response": []
		},
		{
			"name": "READ BY EMAIL",
			"request": {
				"auth": {
					"type": "bearer",
					"bearer": [
						{
							"key": "token",
							"value": "{{jwt_token}}",
							"type": "string"
						}
					]
				},
				"method": "GET",
				"header": [],
				"url": {
					"raw": "localhost:8080/api/v1/user?email=juan@rodriguez.cl",
					"host": [
						"localhost"
					],
					"port": "8080",
					"path": [
						"api",
						"v1",
						"user"
					],
					"query": [
						{
							"key": "email",
							"value": "juan@rodriguez.cl"
						}
					]
				}
			},
			"response": []
		},
		{
			"name": "LOGIN",
			"event": [
				{
					"listen": "test",
					"script": {
						"exec": [
							"// Obtener la respuesta JSON\r",
							"var jsonData = pm.response.json();\r",
							"\r",
							"// Verificar si el token existe en la respuesta\r",
							"if (jsonData.token) {\r",
							"    // Extraer el token\r",
							"    var token = jsonData.token;\r",
							"    // Guardar el token en una variable de entorno\r",
							"    pm.environment.set(\"jwt_token\", token);\r",
							"    }"
						],
						"type": "text/javascript",
						"packages": {}
					}
				}
			],
			"request": {
				"auth": {
					"type": "noauth"
				},
				"method": "POST",
				"header": [],
				"url": {
					"raw": "localhost:8080/login?user=test&encryptedPass=test",
					"host": [
						"localhost"
					],
					"port": "8080",
					"path": [
						"login"
					],
					"query": [
						{
							"key": "user",
							"value": "test"
						},
						{
							"key": "encryptedPass",
							"value": "test"
						}
					]
				}
			},
			"response": []
		}
	]
}